pyspcbridge/__init__.py
pyspcbridge/area.py
pyspcbridge/const.py
pyspcbridge/door.py
pyspcbridge/exceptions.py
pyspcbridge/output.py
pyspcbridge/panel.py
pyspcbridge/spc_error.py
pyspcbridge/spc_http_client.py
pyspcbridge/spc_ws_client.py
pyspcbridge/user.py
pyspcbridge/utils.py
pyspcbridge/websocket.py
pyspcbridge/zone.py
pyspcbridge-0.6.2.dist-info/LICENSE
pyspcbridge-0.6.2.dist-info/METADATA
pyspcbridge-0.6.2.dist-info/WHEEL
pyspcbridge-0.6.2.dist-info/RECORD
