Metadata-Version: 2.1
Name: pyspcbridge
Version: 0.6.2
Summary: Python library for communicating with acre/Vanderbilt SPC alarm system via Lundix's SPC Bridge Generic (Lite)
License: MIT
Author: Lundix IT
Author-email: info@lundix.se
Requires-Python: >=3.11,<4.0
Classifier: License :: OSI Approved :: MIT License
Classifier: Programming Language :: Python :: 3
Classifier: Programming Language :: Python :: 3.11
Classifier: Programming Language :: Python :: 3.12
Classifier: Programming Language :: Python :: 3.13
Requires-Dist: aiohttp (>=3.10.8)
Requires-Dist: httpx (>=0.27.0)
